grabutils/__init__.py
grabutils/bspo.py
grabutils/dictutils.py
grabutils/fileutils.py
grabutils/imgutils.py
grabutils/jspo.py
grabutils/objview.py
grabutils/shutils.py
grabutils/ssh.py
grabutils/strutils.py
grabutils/bs/__init__.py
grabutils/bs/pageobj.py
grabutils/perf/__init__.py
grabutils/perf/timer.py
grabutils/rest/__init__.py
grabutils/rest/client.py
tests/__init__.py
tests/conftest.py
tests/ololo.py
tests/test_bs_pageobj.py
tests/test_dictutils.py
tests/test_fileutils.py
tests/test_objview.py
grabutils-0.0.32.dist-info/LICENSE
grabutils-0.0.32.dist-info/METADATA
grabutils-0.0.32.dist-info/WHEEL
grabutils-0.0.32.dist-info/top_level.txt
grabutils-0.0.32.dist-info/RECORD
