Metadata-Version: 2.1
Name: grabutils
Version: 0.0.32
Summary: Utils and helpers for crawling websites
Home-page: https://github.com/sniter/grabutils
Author: Ilya Babich
Author-email: sniter@gmail.com
License: UNKNOWN
Platform: UNKNOWN
Classifier: Programming Language :: Python :: 3
Classifier: License :: OSI Approved :: MIT License
Classifier: Operating System :: OS Independent
Requires-Python: >=3.6
Provides-Extra: all
Requires-Dist: beautifulsoup4 ; extra == 'all'
Requires-Dist: lxml ; extra == 'all'
Requires-Dist: paramiko[ed25519] ; extra == 'all'
Requires-Dist: scp ; extra == 'all'
Requires-Dist: requests ; extra == 'all'
Requires-Dist: Pillow ; extra == 'all'
Requires-Dist: jmespath ; extra == 'all'
Provides-Extra: bs
Requires-Dist: beautifulsoup4 ; extra == 'bs'
Requires-Dist: lxml ; extra == 'bs'
Provides-Extra: img
Requires-Dist: Pillow ; extra == 'img'
Provides-Extra: jspo
Requires-Dist: jmespath ; extra == 'jspo'
Provides-Extra: rest
Requires-Dist: requests ; extra == 'rest'
Provides-Extra: ssh
Requires-Dist: paramiko[ed25519] ; extra == 'ssh'
Requires-Dist: scp ; extra == 'ssh'
